pyl10nc/__init__.py
pyl10nc/__main__.py
pyl10nc-1.3.2.dist-info/licenses/LICENSE
pyl10nc-1.3.2.dist-info/METADATA
pyl10nc-1.3.2.dist-info/WHEEL
pyl10nc-1.3.2.dist-info/entry_points.txt
pyl10nc-1.3.2.dist-info/top_level.txt
pyl10nc-1.3.2.dist-info/RECORD
