Metadata-Version: 2.4
Name: pyl10nc
Version: 1.3.2
Summary: Python Localization Code Generator from TOML files, JSON, and YAML
Author-email: Shasnow <yukikage@qq.com>
License: MIT
Project-URL: Homepage, https://github.com/Shasnow/pyl10nc
Project-URL: Repository, https://github.com/Shasnow/pyl10nc
Project-URL: Issues, https://github.com/Shasnow/pyl10nc/issues
Keywords: localization,i18n,toml,code-generation
Classifier: Development Status :: 4 - Beta
Classifier: Intended Audience :: Developers
Classifier: License :: OSI Approved :: MIT License
Classifier: Programming Language :: Python :: 3
Classifier: Programming Language :: Python :: 3.8
Classifier: Programming Language :: Python :: 3.9
Classifier: Programming Language :: Python :: 3.10
Classifier: Programming Language :: Python :: 3.11
Classifier: Programming Language :: Python :: 3.12
Classifier: Programming Language :: Python :: 3.13
Requires-Python: >=3.8
License-File: LICENSE
Provides-Extra: yaml
Requires-Dist: PyYAML>=6.0; extra == "yaml"
Dynamic: license-file
